hhlpy/__main__.py
hhlpy/arch.py
hhlpy/hhlpy.py
hhlpy/sympy_wrapper.py
hhlpy/wolframengine_wrapper.py
hhlpy/z3wrapper.py
hhlpy/examples/advanced1.hhl
hhlpy/examples/basic1.hhl
hhlpy/examples/basic10.hhl
hhlpy/examples/basic11.hhl
hhlpy/examples/basic12.hhl
hhlpy/examples/basic13.hhl
hhlpy/examples/basic14.hhl
hhlpy/examples/basic15.hhl
hhlpy/examples/basic16.hhl
hhlpy/examples/basic17.hhl
hhlpy/examples/basic18.hhl
hhlpy/examples/basic19.hhl
hhlpy/examples/basic2.hhl
hhlpy/examples/basic21.hhl
hhlpy/examples/basic22.hhl
hhlpy/examples/basic23.hhl
hhlpy/examples/basic24.hhl
hhlpy/examples/basic25.hhl
hhlpy/examples/basic26.hhl
hhlpy/examples/basic27.hhl
hhlpy/examples/basic28.hhl
hhlpy/examples/basic29.hhl
hhlpy/examples/basic3.hhl
hhlpy/examples/basic31.hhl
hhlpy/examples/basic33.hhl
hhlpy/examples/basic34.hhl
hhlpy/examples/basic35.hhl
hhlpy/examples/basic36.hhl
hhlpy/examples/basic37.hhl
hhlpy/examples/basic38.hhl
hhlpy/examples/basic39.hhl
hhlpy/examples/basic4.hhl
hhlpy/examples/basic40.hhl
hhlpy/examples/basic41.hhl
hhlpy/examples/basic42.hhl
hhlpy/examples/basic43.hhl
hhlpy/examples/basic44.hhl
hhlpy/examples/basic45.hhl
hhlpy/examples/basic46.hhl
hhlpy/examples/basic47.hhl
hhlpy/examples/basic48.hhl
hhlpy/examples/basic49.hhl
hhlpy/examples/basic5.hhl
hhlpy/examples/basic50.hhl
hhlpy/examples/basic52.hhl
hhlpy/examples/basic53.hhl
hhlpy/examples/basic54.hhl
hhlpy/examples/basic55.hhl
hhlpy/examples/basic57.hhl
hhlpy/examples/basic60.hhl
hhlpy/examples/basic7.hhl
hhlpy/examples/basic8.hhl
hhlpy/examples/basic9.hhl
hhlpy/examples/nonlinear1.hhl
hhlpy/examples/nonlinear10.hhl
hhlpy/examples/nonlinear100.hhl
hhlpy/examples/nonlinear102.hhl
hhlpy/examples/nonlinear103.hhl
hhlpy/examples/nonlinear104.hhl
hhlpy/examples/nonlinear109.hhl
hhlpy/examples/nonlinear11.hhl
hhlpy/examples/nonlinear112.hhl
hhlpy/examples/nonlinear116.hhl
hhlpy/examples/nonlinear118.hhl
hhlpy/examples/nonlinear119.hhl
hhlpy/examples/nonlinear12.hhl
hhlpy/examples/nonlinear120.hhl
hhlpy-0.1.0.dist-info/METADATA
hhlpy-0.1.0.dist-info/WHEEL
hhlpy-0.1.0.dist-info/entry_points.txt
hhlpy-0.1.0.dist-info/top_level.txt
hhlpy-0.1.0.dist-info/RECORD
